MANIFEST.in
README.rst
setup.py
django_d2m/__init__.py
django_d2m/d2m.py
django_d2m/test_settings.py
django_d2m/tests.py
django_d2m.egg-info/PKG-INFO
django_d2m.egg-info/SOURCES.txt
django_d2m.egg-info/dependency_links.txt
django_d2m.egg-info/requires.txt
django_d2m.egg-info/top_level.txt
django_d2m.egg-info/zip-safe
django_d2m/testapp/__init__.py
django_d2m/testapp/models.py
django_d2m/testapp/fixtures/initial_data.json